Metadata-Version: 2.1
Name: passhashdb
Version: 0.0.1
Summary: Build and search a password hash database
Home-page: https://gitlab.com/JonathonReinhart/passhashdb
Author: Jonathon Reinhart
Author-email: jonathon.reinhart@gmail.com
License: MIT
Platform: UNKNOWN
Requires-Python: >=3.5
